Metadata-Version: 1.0
Name: audict
Version: 0.0.5
Summary: generates subtitles for video
Home-page: https://github.com/wenzhuart/audict
Author: bamboo
Author-email: wenzhu_art@hotmail.com
License: UNKNOWN
Platform: UNKNOWN
